tornapi/__init__.py
tornapi/errors.py
tornapi/items.py
tornapi/stocks.py
phil0_tornapi-0.2.6.dist-info/LICENSE
phil0_tornapi-0.2.6.dist-info/METADATA
phil0_tornapi-0.2.6.dist-info/WHEEL
phil0_tornapi-0.2.6.dist-info/top_level.txt
phil0_tornapi-0.2.6.dist-info/RECORD
